<?xml version="1.0" encoding="UTF-8"?>

<config_plugin>

    <doctypes>
        <!-- used to create monographic items -->
        <monographic>Monograph</monographic>
        <!-- Document type to register ZDB title data -->
        <zdbRecordType>ZdbTitle</zdbRecordType>
        <!-- document types to create new issue items -->
        <journalType>Periodical</journalType>
        <issueType>PeriodicalVolume</issueType>

        <!-- metadata field for ZDB ID -->
        <zdbId>CatalogIDPeriodicalDB</zdbId>
    </doctypes>

    <processtemplates>
        <!-- process template for monogrpaphic items -->
        <monograph>Standard</monograph>
        <!-- process template to register ZDB title data -->
        <zdbTitle>ZDB_template</zdbTitle>
        <!-- process template for issues-->
        <journal>Standard</journal>
    </processtemplates>


    <vocabularyServerUrl>https://example.com/vocabulary/records/</vocabularyServerUrl>
    <!-- metadata fields for monographic items -->


    <!--

group: contains a list of fields, grouped together
- attribute label contains the name of the group
- attribute documentType determines for which document type it is displayed
- pageName definies on which page the group gets displayed, possible values are data1, data2, data3 for monogrpahs
-->

    <!--
field: individual input field
- label: contains the display name of the field
- rulesetName: name of the metadata field in the ruleset
- displayType: different input types: person, corporate, picklist, input
- metadataLevel: anchor or child (without function) 
- cardinality: 1 = exact one, ? 0 or one, * any, + at least one
- marcMainTag: marc main tag, without function
- marcSubTag: marc sub tag, without function
- validationExpression: regular expression to configure a validation
- validationErrorText: text to display when validation fails
- helpMessage: usefull message to display on screen
- replaceWith: get content from user data
-->


    <group label="Titelinformationen" pageName="data1" documentType="monograph">
        <field rulesetName="TitleDocMain" label="Titel" displayType="input" metadataLevel="anchor" cardinality="1" marcMainTag="245" marcSubTag="a" validationExpression=".+" validationErrorText="Die Angabe ist ein Pflichtfeld" helpMessage="Tragen Sie hier den Titel ein."></field>
        <field rulesetName="TitleDocSub1" label="Untertitel" displayType="input" metadataLevel="anchor" cardinality="*" marcMainTag="245" marcSubTag="b" validationExpression="" validationErrorText="" helpMessage="Hilfetext für Untertitel"></field>
    </group>

    <group label="Verantwortliche: Personen und Körperschaften" pageName="data1" documentType="monograph">

        <field rulesetName="Author" label="Autor*in, beteiligte Person" displayType="person" metadataLevel="anchor" cardinality="*" marcMainTag="100" marcSubTag="a" validationExpression="" validationErrorText="" helpMessage="Lorem ipsum">
            <!--
            <selectfield value="Author" label="Autor" />
            <selectfield value="Artist" label="Künstler" />
            <selectfield value="Translator" label="Übersetzer" />
 -->
            <vocabulary name="PersonRoleTerms" displayField="Bezeichnung" importField="Metadatum" />
        </field>

        <field rulesetName="Author" label="Beteiligte Organisation" displayType="corporate" metadataLevel="anchor" cardinality="*" marcMainTag="110" marcSubTag="a" validationExpression="" validationErrorText="" helpMessage="Lorem ipsum">
            <!--
            <selectfield value="CorporateAuthor" label="Autor" />
            <selectfield value="CorporateArtist" label="Künstler" />
            <selectfield value="CorporateContributor" label="Mitwirkende Körperschaft" />
        -->
            <vocabulary name="CorporateRoleTerms" displayField="Bezeichnung" importField="Metadatum" />
        </field>
    </group>

    <group label="Angaben zur Entstehung" pageName="data1" documentType="monograph">
        <field rulesetName="Edition" label="Auflage, Stand oder Version" displayType="input" metadataLevel="anchor" cardinality="?" marcMainTag="245" marcSubTag="a" validationExpression="" validationErrorText="" helpMessage="Tragen Sie hier den Titel ein."></field>
        <field rulesetName="PublicationYear" label="Erscheinungsjahr" displayType="input" metadataLevel="anchor" cardinality="1" marcMainTag="245" marcSubTag="a" validationExpression="\d{4}" validationErrorText="Geben Sie eiene vierstellige Jahreszahl ein" helpMessage="Tragen Sie hier das Jahr ein."></field>
    </group>

    <group label="Sprache" pageName="data1" documentType="monograph">
        <field rulesetName="DocLanguage" label="Sprache" displayType="dropdown" metadataLevel="anchor" cardinality="+" marcMainTag="245" marcSubTag="a" validationExpression=".+" validationErrorText="Die Angabe ist ein Pflichtfeld" helpMessage="Tragen Sie hier den Titel ein.">
            <selectfield value="ger" label="Deutsch" />
            <selectfield value="eng" label="Englisch" />
        </field>
    </group>

    <group label="Ident-Nummern" pageName="data2" documentType="monograph">
        <field rulesetName="CatalogIDDigital" label="Ident-Nummer" displayType="picklist" metadataLevel="anchor" cardinality="?" marcMainTag="110" marcSubTag="a" validationExpression="" validationErrorText="" helpMessage="Lorem ipsum">
            <selectfield value="ISBN" label="ISBN" />
            <selectfield value="ISMN" label="ISMN" />
            <selectfield value="DOI" label="DOI" />
            <selectfield value="URN" label="URN" />
            <selectfield value="Handle" label="Handle" />
            <selectfield value="UPC" label="UPC" />
            <selectfield value="EAN" label="GTIN/EAN" />
            <selectfield value="OrderNumber" label="Best.-Nr." />
            <selectfield value="Identifikation" label="Eindeutige Identifikation (beliebige Angabe)" />
            <selectfield value="keine" label="keine" />
        </field>
    </group>

    <group label="Beziehungen zu anderen Ressourcen" pageName="data2" documentType="monograph">
        <field rulesetName="TitleUnterreihe" label="Titel der Reihe" displayType="input" metadataLevel="anchor" cardinality="*" marcMainTag="245" marcSubTag="a" validationExpression="" validationErrorText="" helpMessage="Tragen Sie hier den Titel ein."></field>
        <field rulesetName="TitlePartNumber" label="Zählung des Bandes" displayType="input" metadataLevel="anchor" cardinality="*" marcMainTag="245" marcSubTag="a" validationExpression="" validationErrorText="" helpMessage="Tragen Sie hier den Titel ein."></field>
    </group>

    <group label="Beschreibung des Inhalts" pageName="data2" documentType="monograph">
        <field rulesetName="DDC" label="Sachgruppe/Thema" displayType="dropdown" metadataLevel="anchor" cardinality="1" marcMainTag="110" marcSubTag="a" validationExpression="" validationErrorText="" helpMessage="Lorem ipsum">
            <selectfield value="Wert1" label="Wert1" />
            <selectfield value="Wert2" label="Wert2" />
            <selectfield value="Wert3" label="Wert3" />
        </field>
        <field rulesetName="SubjectTopic" label="Schlagwort(e)" displayType="input" metadataLevel="anchor" cardinality="*" marcMainTag="245" marcSubTag="a" validationExpression="" validationErrorText="" helpMessage="Tragen Sie hier den Titel ein."></field>

        <field rulesetName="Abstract" label="Zusammenfassung oder Abstract" displayType="input" metadataLevel="anchor" cardinality="?" marcMainTag="245" marcSubTag="a" validationExpression="" validationErrorText="" helpMessage="Tragen Sie hier den Titel ein."></field>
    </group>


    <group label="Zugriffs- und Rechteinformation" pageName="data3" documentType="monograph">
        <field rulesetName="AccessLicense" label="Zugangsbedingungen" displayType="dropdown" metadataLevel="anchor" cardinality="1" marcMainTag="110" marcSubTag="a" validationExpression="" validationErrorText="" helpMessage="Lorem ipsum" replaceWith="institution-accesscondition">
            <selectfield value="Rechte vorbehalten" label="Rechte vorbehalten" />
            <selectfield value="CC0" label="CC0" />
            <selectfield value="CC BY" label="CC BY" />
            <selectfield value="CC BY-SA" label="CC BY-SA" />
            <selectfield value="CC BY-ND" label="CC BY-ND" />
            <selectfield value="CC BY-NC" label="CC BY-NC" />
            <selectfield value="CC BY-NC-SA" label="CC BY-NC-SA" />
            <selectfield value="CC BY-NC-ND" label="CC BY-NC-ND" />
        </field>
        <field rulesetName="Copyright" label="Rechtestatus" displayType="dropdown" metadataLevel="anchor" cardinality="1" marcMainTag="110" marcSubTag="a" validationExpression="" validationErrorText="" helpMessage="Lorem ipsum">
            <selectfield value="gesperrt" label="gesperrt" />
            <selectfield value="gesperrt, Zugriff nur nach Antrag" label="gesperrt, Zugriff nur nach Antrag" />
            <selectfield value="beschränkt" label="beschränkt" />
            <selectfield value="teil-beschränkt" label="teil-beschränkt" />
            <selectfield value="unbeschränkt" label="unbeschränkt" />
        </field>
        <field rulesetName="URL" label="Adresse der Originalveröffentlichung (URL)" displayType="input" metadataLevel="anchor" cardinality="?" marcMainTag="245" marcSubTag="a" validationExpression="" validationErrorText="" helpMessage="Tragen Sie hier den Titel ein."></field>
    </group>

    <group label="Anmerkungen" pageName="data3" documentType="monograph">
        <field rulesetName="InternalNote" label="Mitteilung (nicht-öffentlich)" displayType="input" metadataLevel="anchor" cardinality="?" marcMainTag="110" marcSubTag="a" validationExpression="" validationErrorText="" helpMessage="Lorem ipsum"></field>
        <field rulesetName="FSK" label="Angabe zur freiwilligen Selbstkontrolle" displayType="dropdown" metadataLevel="anchor" cardinality="1" marcMainTag="110" marcSubTag="a" validationExpression="" validationErrorText="" helpMessage="Lorem ipsum">
            <selectfield value="Ohne Altersbeschränkung" label="Ohne Altersbeschränkung" />
            <selectfield value="Freigegeben ab sechs Jahren" label="Freigegeben ab sechs Jahren" />
            <selectfield value="Freigegeben ab zwölf Jahren" label="Freigegeben ab zwölf Jahren" />
            <selectfield value="Freigegeben ab sechzehn Jahren" label="Freigegeben ab sechzehn Jahren" />
            <selectfield value="Freigegeben ab achtzehn Jahren" label="Freigegeben ab achtzehn Jahren" />
        </field>
    </group>


    <!-- metadata for journals -->

    <group label="Titelinformationen" pageName="newTitle" documentType="journal">
        <field rulesetName="TitleDocMain" label="Titel" displayType="input" metadataLevel="anchor" cardinality="1" marcMainTag="245" marcSubTag="a" validationExpression=".+" validationErrorText="Die Angabe ist ein Pflichtfeld" helpMessage="Tragen Sie hier den Titel ein."></field>
        <field rulesetName="TitleDocSub1" label="Untertitel" displayType="input" metadataLevel="anchor" cardinality="*" marcMainTag="245" marcSubTag="b" validationExpression="" validationErrorText="" helpMessage="Hilfetext für Untertitel"></field>
    </group>

    <group label="Verantwortliche:  Körperschaften" pageName="newTitle" documentType="journal">

        <field rulesetName="Author" label="Beteiligte Organisation" displayType="corporate" metadataLevel="anchor" cardinality="*" marcMainTag="110" marcSubTag="a" validationExpression="" validationErrorText="" helpMessage="Lorem ipsum">
            <!--
            <selectfield value="CorporateAuthor" label="Autor" />
            <selectfield value="CorporateArtist" label="Künstler" />
            <selectfield value="CorporateContributor" label="Mitwirkende Körperschaft" />
        -->
            <vocabulary name="CorporateRoleTerms" displayField="Bezeichnung" importField="Metadatum" />
        </field>
    </group>


    <group label="Angaben zur Entstehung" pageName="newTitle" documentType="journal">
        <field rulesetName="PublicationStart" label="Erscheinungsdatum der ersten Ausgabe" displayType="input" metadataLevel="anchor" cardinality="?" marcMainTag="245" marcSubTag="a" validationExpression="\d{4,8}" validationErrorText="TTMMJJJJ und/oder MMJJJJJ und/oder JJJJ" helpMessage="TTMMJJJJ und/oder MMJJJJJ und/oder JJJJ"></field>
        <field rulesetName="PublicationRun" label="Nummerierung der Erstausgabe (Jahrgangs-, Heftangabe etc.)" displayType="input" metadataLevel="anchor" cardinality="1" marcMainTag="264" marcSubTag="c" validationExpression="" validationErrorText="" helpMessage="Tragen Sie hier das Jahr ein."></field>
    </group>
    <group label="Sprache" pageName="newTitle" documentType="journal">
        <field rulesetName="DocLanguage" label="Sprache" displayType="dropdown" metadataLevel="anchor" cardinality="+" marcMainTag="245" marcSubTag="a" validationExpression=".+" validationErrorText="Die Angabe ist ein Pflichtfeld" helpMessage="Tragen Sie hier den Titel ein.">
            <selectfield value="ger" label="Deutsch" />
            <selectfield value="eng" label="Englisch" />
        </field>
    </group>

    <group label="Ident-Nummern" pageName="newTitle" documentType="journal">
        <field rulesetName="CatalogIDDigital" label="Ident-Nummer" displayType="picklist" metadataLevel="anchor" cardinality="*" marcMainTag="110" marcSubTag="a" validationExpression="" validationErrorText="" helpMessage="Lorem ipsum">
            <selectfield value="ISSN" label="ISSN" />
            <selectfield value="DOI" label="DOI" />
            <selectfield value="URN" label="URN" />
            <selectfield value="Handle" label="Handle" />
            <selectfield value="Identifikation" label="Eindeutige Identifikation (beliebige Angabe)" />
            <selectfield value="keine" label="keine" />
        </field>
    </group>


    <group label="Beschreibung des Inhalts" pageName="newTitle" documentType="journal">
        <field rulesetName="DDC" label="Sachgruppe/Thema" displayType="dropdown" metadataLevel="anchor" cardinality="1" marcMainTag="110" marcSubTag="a" validationExpression="" validationErrorText="" helpMessage="Lorem ipsum">
            <selectfield value="Wert1" label="Wert1" />
            <selectfield value="Wert2" label="Wert2" />
            <selectfield value="Wert3" label="Wert3" />
        </field>
    </group>

    <group label="Zugriffs- und Rechteinformation" pageName="newTitle" documentType="journal">
        <field rulesetName="AccessLicense" label="Zugangsbedingungen" displayType="dropdown" metadataLevel="anchor" cardinality="1" marcMainTag="110" marcSubTag="a" validationExpression="" validationErrorText="" helpMessage="Lorem ipsum" replaceWith="institution-accesscondition">
            <selectfield value="Rechte vorbehalten" label="Rechte vorbehalten" />
            <selectfield value="CC0" label="CC0" />
            <selectfield value="CC BY" label="CC BY" />
            <selectfield value="CC BY-SA" label="CC BY-SA" />
            <selectfield value="CC BY-ND" label="CC BY-ND" />
            <selectfield value="CC BY-NC" label="CC BY-NC" />
            <selectfield value="CC BY-NC-SA" label="CC BY-NC-SA" />
            <selectfield value="CC BY-NC-ND" label="CC BY-NC-ND" />
        </field>
        <field rulesetName="Copyright" label="Rechtestatus" displayType="dropdown" metadataLevel="anchor" cardinality="1" marcMainTag="110" marcSubTag="a" validationExpression="" validationErrorText="" helpMessage="Lorem ipsum">
            <selectfield value="gesperrt" label="gesperrt" />
            <selectfield value="gesperrt, Zugriff nur nach Antrag" label="gesperrt, Zugriff nur nach Antrag" />
            <selectfield value="beschränkt" label="beschränkt" />
            <selectfield value="teil-beschränkt" label="teil-beschränkt" />
            <selectfield value="unbeschränkt" label="unbeschränkt" />
        </field>
        <field rulesetName="URL" label="Adresse der Originalveröffentlichung (URL)" displayType="input" metadataLevel="anchor" cardinality="?" marcMainTag="245" marcSubTag="a" validationExpression="" validationErrorText="" helpMessage="Tragen Sie hier den Titel ein."></field>
    </group>

    <group label="Anmerkungen" pageName="data2" documentType="journal">
        <field rulesetName="InternalNote" label="Mitteilung (nicht-öffentlich)" displayType="input" metadataLevel="anchor" cardinality="?" marcMainTag="110" marcSubTag="a" validationExpression="" validationErrorText="" helpMessage="Lorem ipsum"></field>
    </group>


    <!-- metadata for issues -->


    <group label="Titelinformationen" pageName="newIssue" documentType="issue">
        <field rulesetName="TitleDocMain" label="Eigenständiger Titel des Heftes" displayType="input" metadataLevel="child" cardinality="?" marcMainTag="245" marcSubTag="a" validationExpression="" validationErrorText="" helpMessage="Tragen Sie hier den Titel ein."></field>
    </group>


    <group label="Angaben zur Entstehung" pageName="newIssue" documentType="issue">
        <field rulesetName="PublicationYear" label="Erscheinungsdatum" displayType="input" metadataLevel="child" cardinality="1" marcMainTag="245" marcSubTag="a" validationExpression="\d{4,8}" validationErrorText="" helpMessage="Tragen Sie hier den Titel ein."></field>
        <field rulesetName="VolumeNo" label="Bandnummer" displayType="input" metadataLevel="child" cardinality="1" marcMainTag="245" marcSubTag="a" validationExpression="\d+" validationErrorText="Nur Ziffern" helpMessage="Tragen Sie hier das Jahr ein."></field>
        <field rulesetName="CurrentNo" label="Jahrgang" displayType="input" metadataLevel="child" cardinality="1" marcMainTag="245" marcSubTag="a" validationExpression=".+" validationErrorText="Geben Sie eiene vierstellige Jahreszahl ein" helpMessage="Label."></field>
        <field rulesetName="PartNumber" label="Heftnummer" displayType="input" metadataLevel="anchor" cardinality="?" marcMainTag="245" marcSubTag="a" validationExpression="" validationErrorText="" helpMessage="Unklar wozu das dienen soll"></field>
    </group>


    <group label="Beziehungen zu anderen Ressourcen" pageName="newIssue" documentType="issue">
        <!-- list all valid titles of the current customer/institution -->
        <field rulesetName="" label="Zeitschriftentitel" displayType="journaltitles" metadataLevel="child" cardinality="1" marcMainTag="110" marcSubTag="a" validationExpression="" validationErrorText="" helpMessage="Lorem ipsum"></field>
    </group>

    <!-- default values are taken from journal title values -->
    <group label="Zugriffs- und Rechteinformation" pageName="newIssue" documentType="issue">
        <field rulesetName="AccessLicense" label="Zugangsbedingungen" displayType="dropdown" metadataLevel="anchor" cardinality="1" marcMainTag="110" marcSubTag="a" validationExpression="" validationErrorText="" helpMessage="Lorem ipsum" replaceWith="institution-accesscondition">
            <selectfield value="Rechte vorbehalten" label="Rechte vorbehalten" />
            <selectfield value="CC0" label="CC0" />
            <selectfield value="CC BY" label="CC BY" />
            <selectfield value="CC BY-SA" label="CC BY-SA" />
            <selectfield value="CC BY-ND" label="CC BY-ND" />
            <selectfield value="CC BY-NC" label="CC BY-NC" />
            <selectfield value="CC BY-NC-SA" label="CC BY-NC-SA" />
            <selectfield value="CC BY-NC-ND" label="CC BY-NC-ND" />
        </field>
        <field rulesetName="Copyright" label="Rechtestatus" displayType="dropdown" metadataLevel="anchor" cardinality="1" marcMainTag="110" marcSubTag="a" validationExpression="" validationErrorText="" helpMessage="Lorem ipsum">
            <selectfield value="gesperrt" label="gesperrt" />
            <selectfield value="gesperrt, Zugriff nur nach Antrag" label="gesperrt, Zugriff nur nach Antrag" />
            <selectfield value="beschränkt" label="beschränkt" />
            <selectfield value="teil-beschränkt" label="teil-beschränkt" />
            <selectfield value="unbeschränkt" label="unbeschränkt" />
        </field>
        <field rulesetName="URL" label="Adresse der Originalveröffentlichung (URL)" displayType="input" metadataLevel="anchor" cardinality="?" marcMainTag="245" marcSubTag="a" validationExpression="" validationErrorText="" helpMessage="Tragen Sie hier den Titel ein."></field>
    </group>

    <group label="Anmerkungen" pageName="newIssue" documentType="issue">
        <field rulesetName="InternalNote" label="Mitteilung (nicht-öffentlich)" displayType="input" metadataLevel="anchor" cardinality="?" marcMainTag="110" marcSubTag="a" validationExpression="" validationErrorText="" helpMessage="Lorem ipsum"></field>
    </group>


    <additionalMetadata>
        <field rulesetName="PublisherName" defaultValue="" replaceWith="institution" />
        <field rulesetName="PlaceOfPublication" defaultValue="" replaceWith="institution-city" />
        <field rulesetName="ContentType" defaultValue="Text" replaceWith="" />
        <field rulesetName="MediaType" defaultValue="Computermedien" replaceWith="" />
        <field rulesetName="DataMediumType" defaultValue="Online-Ressource" replaceWith="" />


        <field rulesetName="ActionNote" defaultValue="Archivierung/Langzeitarchivierung geplant" replaceWith="" />
        <field rulesetName="LegalBasis" defaultValue="PEBE" replaceWith="" />
        <field rulesetName="ISIL" defaultValue="DE-109" replaceWith="" />
        <field rulesetName="DigitalOrigin" defaultValue="born-digital" replaceWith="" />
        <field rulesetName="TypeOfResource" defaultValue="Text" replaceWith="" />


    </additionalMetadata>


</config_plugin>
